gcmai/__init__.py
gcmai/db.py
gcmai-0.1.0.dist-info/METADATA
gcmai-0.1.0.dist-info/WHEEL
gcmai-0.1.0.dist-info/entry_points.txt
gcmai-0.1.0.dist-info/RECORD
